{
  "about clinic": "Despre clinică",
  "accept invitation": "Acceptă invitația",
  "accept invitation message": "Completați câmpurile de mai jos pentru a accepta invitația.",
  "access_blocked": "Acces blocat",
  "access_blocked_message": "Accesul Dvs. la aceasta clinica a fost blocat, vă rugăm să contactați managerul clinicii pentru mai multe informații.",
  "account_created_success": "Contul a fost creat cu succes. Vă rugăm să introduceți detaliile clinicii.",
  "account information": "Detalii cont",
  "account settings": "Setări cont",
  "actions": "Acțiuni",
  "activity logs": "Jurnal activități",
  "add a comment": "Adaugă un comentariu...",
  "add appointment": "Adaugă o programare",
  "add_appointment_cabinet": "Cabinet",
  "add_cabinet": "Adaugă cabinet",
  "add category": "Adaugă categorie",
  "add doctor": "Adaugă doctor",
  "added by": "Adăugat de %{completedby} la data %{date}",
  "addedby": "Adăugat de",
  "add holiday": "Adaugă vacanță",
  "add image": "Adaugă imagine",
  "add manager": "Adaugă manager",
  "add_new_appointment": "Adaugă o programare nouă",
  "add_new_card": "Adaugă card nou",
  "add new color": "Adăugați o culoare nouă",
  "add new column": "Adaugă coloană",
  "add new user": "Adaugă utilizator",
  "add note": "Adaugă notă",
  "add one +": "Adaugă +",
  "add patient": "Adaugă pacient",
  "addpatientxrayimage": "A adăugat o imagine X-Ray la un pacient",
  "add pause": "Adaugă pauză",
  "add payment": "Adaugă achitare",
  "add rate": "Adaugă curs valutar",
  "add receptionist": "Adaugă recepționist",
  "add_seats": "Adaugă locuri",
  "add service": "Adaugă serviciu",
  "add_tag_to_patient": "Adaugă etichetă",
  "add_to_apple_calendar": "Adaugă în Apple Calendar",
  "add_to_google_calendar": "Adaugă în Google Calendar",
  "add user": "Adaugă utilizator",
  "add_xray_image": "Adaugați imaginea X-Ray",
  "administrators": "Manageri",
  "all": "Toți",
  "all_articles": "Toate articolele",
  "all categories": "Toate categoriile",
  "all doctors": "Toți doctorii",
  "allow_access": "Deschide accesul",
  "all services": "Toate serviciile",
  "all statuses": "Toate statuturile",
  "all_tags": "Toate",
  "all time": "Tot timpul",
  "all users": "Toți utilizatorii",
  "already have an account": "Deja am un cont",
  "amount": "Suma",
  "analytics": "Analitică",
  "analytics_clients_new_old": "Clienți noi / Clienți repetați",
  "analytics_clients_source": "Sursa clienților",
  "analytics_doctor_conversion": "Conversie / Medic",
  "analytics_doctor_income": "Venit / Medic",
  "analytics_doctor_visits": "Vizite / Medic",
  "analytics_executed": "Efectuate",
  "executed": "Efectuate",
  "efectuate": "Efectuate",
  "analytics_paid_unpaid": "Achitat / Datorii",
  "analytics_planned": "Planificate",
  "planned": "Planificate",
  "planificate": "Planificate",
  "analytics_services_completed_planned": "Servicii efectuate / planificate",
  "analytics_total_messages": "Total mesaje trimise",
  "analytics_total_visits": "Total vizite",
  "analytics_treated_patients": "Pacienți cu plan de tratament",
  "animate appointments before": "Notifică despre programare din timp",
  "api_address": "Adresa API",
  "api_key": "Cheia API",
  "app initialization": "Inițializarea aplicației",
  "applicable on all teeth": "Aplicabil pe toată dantura",
  "applicable on single tooth": "Aplicabil pe un singur dinte",
  "application settings": "Setări aplicație",
  "apply": "Aplică",
  "apply filters": "Aplică filtrele",
  "apply to all": "Aplică la toate",
  "appointment": "Programare",
  "appointment_animation_timer": "Indică cu cât timp înainte trebuie animate programările",
  "appointment_cabinet": "Cabinet",
  "appointment_create": "Crează programare",
  "appointment_createNew": "Creează programare nouă",
  "appointment_createPatient": "Crează pacient",
  "appointment_date": "Data",
  "appointment_details": "Detalii programare",
  "appointment_doctor": "Doctor",
  "appointment_hours": "Ora",
  "appointment_name": "Nume Prenume",
  "appointment_newClient": "Client nou",
  "appointment_noOptions": "Nu sunt opțiuni pentru afișare",
  "appointment_noPatient": "Nici un client selectat",
  "appointment_notes": "Notițe",
  "appointment_patient": "Pacient",
  "appointment_phone": "Telefon",
  "appointment_placeholder": "Scrie pentru a căuta",
  "appointments": "Programări",
  "appointment_searching": "Căutare",
  "appointment_service": "Serviciu",
  "appointments notes": "Vizite",
  "appointment_source": "Sursa",
  "appointment status": "Statutul programării",
  "appointment_to_doctor": "Programare la medic",
  "appointment_urgent": "Programare urgentă",
  "app_settings_tags": "Etichetele pacienților",
  "app_settings_time_before_on_site": "Timp înainte de a fi pe loc",
  "are you sure you want to delete this category?": "Sunteți sigur(ă) că doriți să ștergeți această categorie?",
  "are you sure you want to delete this service?": "Sunteți sigur(ă) că doriți să ștergeți acest serviciu?",
  "are you sure you want to delete this user?": "Sunteți sigur(ă) că vreți sa ștergeți acest utilizator?",
  "are you sure you want to restore this service?": "Sunteți sigur(ă) că doriți să restabiliți acest serviciu?",
  "article_updated_at": "Actualizat la data {1}",
  "at": "la",
  "authenticate with yclients account": "Autentificațivă cu contul de Yclients",
  "authentication": "Autentificare",
  "back_to_payment_history": "Înapoi la istoria plăților",
  "billing_details": "Detalii plăți",
  "birthday": "Data nașterii",
  "birthdaycongrats": "Felicitări cu ziua de naștere",
  "birthdaycongratsdesc": "Acest mesaj va fi transmis pacienților la ziua lor de naștere (dacă este indicată).",
  "message language": "Limba în care e scris mesajul",
  "block_access": "Blochează accesul",
  "braces": "Aparat dentar",
  "braces service": "Serviciu pentru aparatul dentar",
  "braces settings": "Setări aparate dentare",
  "budget": "Buget",
  "cabinet_name_exists": "Un cabinet cu așa nume deja există.",
  "calendar": "Calendar",
  "calendar legend": "Legenda statuturilor",
  "call_answered": "Discuția a avut loc",
  "call_busy": "Ocupat",
  "call_direction_with_time": "Apel de %{first} %{second}",
  "call_download": "Descarcă",
  "call_failed": "Apelul a eșuat",
  "call_from": "de la",
  "call_incoming": "Intrare",
  "call_listen": "Ascultă",
  "call_noanswer": "Fără răspuns",
  "call_outgoing": "Ieșire",
  "call_to": "spre",
  "call_unknown": "Statut necunoscut",
  "can": "Poate",
  "cancel": "Amână",
  "canceled": "Anulat",
  "canceled_by_patient": "Anulată de pacient",
  "canceled reason": "Motivul anulării",
  "canceledreason": "Motivul anulării",
  "cancel_schedule": "Anulează",
  "cancel_schedule_message": "Din ce motiv doriți să anulați vizita la medic?",
  "cancel_schedule_title": "Anulare programare",
  "cancel_subscription_confirmation": "Sunteți sigur că doriți să anulați subscripția?",
  "can_manage_others_schedules": "Poate gestiona programările altora",
  "can_manage_own_schedules": "Poate gestiona singur programările",
  "cannot": "Nu Poate",
  "cashier": "Casier",
  "categories": "Categorii",
  "change column color": "Modifică culoarea",
  "change password message": "Parola trebuie să conțină minim 6 caractere.",
  "chart_clientsnewreturn": "Clienți noi / Clienți repetați",
  "chart_clientssource": "Sursa clienților",
  "chart_doctorsconversion": "Conversie / Medic",
  "chart_doctorsincome": "Venit / Medic",
  "chart_doctorsvisits": "Vizite / Medic",
  "chart_income": "Achitat / Datorii",
  "chart_messages": "Total mesaje trimise",
  "chart_services": "Servicii efectuate / planificate",
  "chart_treatedclients": "Pacienți cu plan de tratament",
  "chart_visits": "Total vizite",
  "checkout_no_services": "Nu ați selectat nici un serviciu.",
  "checkout_select_below": "Selectați serviciile introducând numele lor în câmpul de mai jos.",
  "choose match": "Alegeți câmpul",
  "chose...": "Alege...",
  "click on button below to accept the invitation": "Dați click pe butonul de mai jos pentru a accepta invitația",
  "clinic": "Clinica",
  "clinic_cabinet_confirmation_request": "Sunteți sigur că doriți să stergeți acest cabinet",
  "clinic_cabinet_doctor_deletion_confirmation": "Sunteți siguri că doriți să elminați acest medic",
  "clinic_cabinets": "Cabinetele clinicii",
  "clinic_cabinets_tag_field": "Adaugă cabinet nou",
  "clinic_cabinets_tag_helper": "Introduceți numele cabinetului și apăsați Enter pentru a salva",
  "clinic currency": "Valuta clinicii",
  "cliniccurrencyatpaymenttime": "Valută",
  "clinic_current_cabinets": "Cabinete curente",
  "clinic_delete_requested": "Cerere primită",
  "clinic_delete_requested_message": "Cererea Dvs. a fost primită, în scurt timp vă vom contacta pentru a confirma toate detaliile.",
  "clinic_has_no_working_hours": "Clinica are zi liberă pentru {1}.",
  "clinic name": "Denumire clinică",
  "clinic profit": "Profitul clinicii",
  "clinic_settings": "Setările clincii",
  "close": "Închide",
  "column name": "Denumirea coloanei",
  "comment": "Comentariu",
  "company details": "Detalii companie",
  "completedat": "Data finisării",
  "completed by": "finisat de %{completedby} la data %{date}",
  "completedby": "Finisat de",
  "complete_deal": "Confirmă",
  "completed. free.": "Finisat. Gratuit.",
  "completed not paid": "Finisat ne achitat",
  "completednotpaid": "Finisat ne achitat",
  "completedpaid": "Achitat",
  "completed services": "Serviciile efectuate",
  "confirm": "Confirmă",
  "confirmation": "Confirmare",
  "confirmation link": "Link de confirmare",
  "confirmed": "Confirmat",
  "confirming schedule": "Confirmăm programarea...",
  "confirm new password": "Confirmați parola nouă",
  "confirm password": "Confirmați parola nouă",
  "connect": "Conectează",
  "connect another page": "Conectați altă pagină",
  "connected_facebook_page": "Conectat la pagina {1}",
  "connect facebook": "Conectează pagina de Facebook",
  "connect_social_message": "Conectați rețelele sociale pentru a genera mai multe leaduri și a crește numarul de clienți.",
  "connect_social_networks": "Conectați rețelele sociale",
  "country": "Țara",
  "country code": "Codul țării",
  "covid_notice": "Dacă aveți febră, tuse, dureri ale gâtului sau alte simptome similare virusului COVID-19, vă rugăm să ne anunțați prealabil și să suspendati vizita. Vă mulțumim pentru înțelegere!",
  "covid_notice_title": "*Important!",
  "create": "Crează",
  "createappointment": "A creat o programare",
  "createcategory": "A creat o categorie",
  "create clinic": "Crează clinică",
  "createClinic": "A creat o clinică",
  "createclinicpaymentaction": "A înregistrat o achitare",
  "created at": "Creat la data",
  "created by": "Creat de",
  "createinvoiceaction": "A creat un invoice",
  "createinvoiceserviceaction": "A fost adăugat un serviciu în invoice",
  "create message": "Creează mesaj",
  "create new account": "Creează cont",
  "create new password": "Creează parola nouă",
  "createnoteaction": "A creat o notiță",
  "create patient": "Adaugă pacient",
  "createpatient": "A creat un pacient",
  "createpatientaction": "A creat pacientul",
  "createpatientfromschedule": "A creat un pacient de la programare",
  "createpatientfromscheduleaction": "A creat un pacient de la programare",
  "createpatientnote": "A adaugat o notă la un pacient",
  "createscheduleaction": "A creat o programare",
  "createservice": "A creat un serviciu",
  "createtreatmentplanserviceaction": "A adăugat un serviciu la planul de tratament",
  "createuser": "A creat un utilizator",
  "createvisitaction": "A creat o vizită",
  "crm_add_reminder": "Adaugă sarcină",
  "crm_columns": "Coloane",
  "crm_filter_all_deals": "Toate",
  "crm_filter_all_reminders": "Toate",
  "crm_filter_closed_successfully": "Finisate cu succes",
  "crm_filter_current_week_reminders": "Următoarele 7 zile",
  "crm_filter_expired_tasks": "Expirate",
  "crm_filter_my_deals": "Doar ale mele",
  "crm_filter_not_realized": "Nerealizate",
  "crm_filter_opened_deals": "Deschise",
  "crm_filter_shortcuts_expired_tasks": "Cu sarcini expirate",
  "crm_filter_shortcuts_today_reminders": "Cu sarcini pentru azi",
  "crm_filter_states": "Statuturi",
  "crm_filter_today_reminders": "Pentru azi",
  "crm_filter_tomorrow_reminders": "Pentru mâine",
  "crm_filter_without_tasks": "Fără sarcini",
  "crm_log_action_changeclinic": "A modificat clinica",
  "crm_log_action_changestatus": "A modificat statutul",
  "crm_log_action_createschedule": "A creat o programare pentru data",
  "crm_log_action_linkpatient": "A atribuit pacientul",
  "crm_log_action_removed": "Acțiune în jurnal eliminată",
  "crm_move_to_clinic": "Mută la altă filială",
  "crm_new_note": "Notiță nouă",
  "crm_new_reminder": "Sarcină nouă",
  "crm_no_reminders": "Nu sunt sarcini",
  "crm_reminder_at": "la ora",
  "crm_reminder_complete": "Finalizează",
  "crm_reminder_date": "Pentru",
  "crm_reminder_enter_result": "Adăugați rezultatul sarcinii",
  "crm_reminder_for": "Pentru",
  "crm_reminder_result": "Rezultat",
  "crm_reminders": "Sarcini",
  "crm_reminders_all_tasks": "Toate sarcinile",
  "crm_reminders_completed_tasks": "Sarcini finisate",
  "crm_reminders_expired_tasks": "Sarcini expirate",
  "crm_reminders_my_tasks": "Sarcinile mele",
  "crm_reminder_today": "Azi la ora",
  "crm_reminder_type": "Tip",
  "crm_reminder_type_contact": "Apel",
  "crm_reminder_type_meeting": "Întâlnire",
  "crm_reminder_user": "Responsabil",
  "crm_settings": "Setări CRM",
  "csv_max_rows_exceeded": "Fișierul încărcat conține mai multe rânduri decât numărul maximal permis.",
  "currency": "Valută",
  "current_bill": "Taxa curentă",
  "current password": "Parola curentă",
  "current password is required": "Introduce-ți parola curentă",
  "date": "Data",
  "dateandtime": "Timp început",
  "day": "Zi",
  "day off": "Zi liberă",
  "day schedules": "Programările pentru o zi",
  "days starting today": "zile de astăzi",
  "days up to today": "zile până astăzi",
  "deal_phone_call_date": "{1} Apel de {2} {3}: {4}",
  "debt": "Datorii",
  "debts": "Datorii",
  "default_card": "Card implicit",
  "default currency": "Valuta de bază",
  "delaytime": "Timpul întârzierii",
  "delete": "Șterge",
  "delete appointment": "Șterge programare",
  "deleteappointment": "A șters o programare",
  "delete appointment message": "Sunteți sigur(ă) că doriți să ștergeți această programare?",
  "delete category": "Șterge categorie",
  "deletecategory": "A șters o categorie",
  "delete clinic": "Șterge clinică",
  "delete_clinic_message": "Sunteți sigur că doriți să ștergeți clinica curentă?",
  "delete column": "Șterge coloana",
  "delete_crm_column": "Ștergeți {1}",
  "delete_crm_column_message": "Sunteți sigur(ă) că doriți să ștergeți această coloană?",
  "deleted": "Șters",
  "delete_deal_message": "Sunteți sigur(ă) că doriți să ștergeți aceste date?",
  "delete_deal_title": "Șterge titlu",
  "deletedinvoiceaction": "A anulat o achitare",
  "delete image": "Șterge imagine",
  "deleteimageconfirmation": "Vă rugăm să confirmați că doriți să ștergeți această imagine.",
  "delete_invitation": "Ștergeți invitația",
  "delete_invitation_message": "Sunteți sigur(ă) că doriți să ștergeți invitația?",
  "delete message": "Șterge mesaj",
  "delete_message_desc": "Sunteți sigur(ă) că doriți să ștergeți acest mesaj?",
  "deletenoteaction": "A șters o notiță",
  "delete patient": "Șterge pacient",
  "deletepatient": "A șters un pacient",
  "delete_patient_message": "Sunteți sigur(ă) că doriți să ștergeți acest pacient?",
  "deletescheduleaction": "A șters o programare",
  "delete service": "Șterge serviciu",
  "deleteservice": "A șters un serviciu",
  "delete_subscription": "Rezilierea contractului",
  "delete_subscription_info": "La rezilierea contractului nu se va percepe taxă conform planului selectat, iar accesul la aplicație va fi limitat.",
  "delete user": "Șterge utilizator",
  "deleteuser": "A șters un utilizator",
  "description": "Descriere",
  "destination": "Destinația",
  "details": "Detalii",
  "diagnosis": "Diagnostică",
  "did not came": "Nu au venit",
  "did not come": "Nu a venit",
  "didn't show up": "Nu a venit",
  "disable": "Dezactivează",
  "disconnect": "Deconectează",
  "discount": "Reducere",
  "discount_notice": "Salvează 15% din tariful lunar",
  "doctor": "Doctor",
  "doctor_calendar_color": "Culoarea programărilor in calendar",
  "doctor_do_not_provide_service": "Doctorul selectat nu prestează acest serviciu!",
  "doctor_is_fired": "Doctorul este concediat!",
  "doctorname": "Nume doctor",
  "doctor part": "Salariul doctorului",
  "doctors": "Doctori",
  "doctors statistics": "Statistica doctorilor",
  "doctors who provide this service": "Doctori care oferă acest serviciu",
  "doctor_vacation_message": "Doctorul este in vacanță pentru ziua dată",
  "domain name": "Numele domenului",
  "don't have an account": "Nu ai un cont",
  "duration": "Durata",
  "edit": "Editează",
  "edit appointment": "Editează programare",
  "editappointment": "A editat o programare",
  "edit category": "Editează categorie",
  "editcategory": "A editat o categorie",
  "editclinic": "A editat clinica",
  "edit_connection": "Editează conexiunea",
  "edit message": "Editează mesaj",
  "editpatient": "A editat un pacient",
  "edit_pause": "Editează pauza",
  "edit profile": "Editează cont",
  "edit service": "Editează serviciu",
  "editservice": "A editat un serviciu",
  "edit user": "Editează utilizator",
  "edituser": "A editat un utilizator",
  "editvisitnote": "A editat nota la vizită",
  "edit_working_hours": "Editează programul de lucru",
  "email": "Email",
  "email_invalid_message": "Adresa de email nu este validă",
  "email_with_instructions_was_sent": "V-am expediat un email cu instrucțiuni",
  "enable": "Activează",
  "end time": "Sfârșit",
  "endtime": "Timp sfârșit",
  "enter a new password": "Introduce o parolă nouă",
  "enter category name": "Introduceți denumirea categoriei",
  "enter doctor name or phone": "Introduceți numele sau numărul de telefon",
  "enter guide name": "Introduceți numele ghidului",
  "enter new message": "Introduce un mesaj nou",
  "enter new note": "Introduceți o nouă notiță",
  "enter patient name or phone": "Introduceți numele sau numărul de telefon",
  "enter reason below": "Introduceți motivul mai jos",
  "enter service name": "Introduceți numele serviciului",
  "enter_the_note": "Introduceți nota",
  "euro debt": "Datorie Euro",
  "exchange rate": "Curs valutar",
  "exchangeratevalueatpaymenttime": "Cursul valutar",
  "executedcount": "Executat",
  "existent patient": "Pacient existent",
  "expectations": "Programați",
  "fallen brackets": "Brackets căzuți",
  "fill_required_fields": "Completați toate câmpurile obligatorii.",
  "filter": "Filtre",
  "finalize": "Finalizează",
  "finalize treatment": "Finalizare tratament",
  "finalizetreatment": "A finisat un tratament",
  "finalizing_treatment": "Se finalizează tratamentul",
  "final phase": "Etapa finală",
  "finished": "Finisat",
  "fired": "Concediat",
  "first name": "Prenume",
  "firstname": "Nume",
  "first_n_last_name": "Nume Prenume",
  "forgot your password": "Ai uitat parola?",
  "for payment": "Spre achitare",
  "friday": "Vineri",
  "friend": "Prieteni",
  "from": "din",
  "fullname": "Nume deplin",
  "gender": "Sex",
  "general": "General",
  "general statistics": "Statistica generală",
  "go back": "Înapoi",
  "go_to": "Mergeți la",
  "go to home": "La pagina principală",
  "help_crm_add_reminder_message": "Apăsați aici pentru a adăuga o sarcina nouă",
  "help_tech_support_message": "Apăsați aici dacă ați întâmpinat careva probleme în utilizarea aplicației sau a apărut vreo eroare, pentru a discuta cu suportul tehnic.",
  "hidden": "Ascuns",
  "hide from calendar": "Ascunde din calendar",
  "history of changes": "Istoria modificarilor",
  "holidaycongrats": "Felicitări cu ocazia de sărbătoare",
  "holidaycongratsdesc": "Acest mesaj va fi transmis la toți pacienții în fiecare an la data selectată mai jos",
  "holidays": "Vacanțe",
  "hour": "Ora",
  "hours": "Ore",
  "how long the patient was late": "Cu cât timp va întârzia pacientul",
  "how_to_get_api_info": "Cum găsesc aceste date?",
  "how_to_get_moizvonki_data": "Cum să obțin datele API pentru Moizvonki.ru?",
  "id": "Indentificator",
  "importedeurodebt": "Datorie Euro importată",
  "import_end_time": "Timp sfârșit",
  "importing data in progress": "Importare date în progres",
  "import_n_patients": "Importați {1} pacienți",
  "import_n_schedules": "Importați {1} programări",
  "import_n_services": "Importați {1} servicii",
  "import patients": "Importare pacienți",
  "import schedules": "Importare programări",
  "import services": "Importează servicii",
  "import_services_note": "Notă: Serviciile fără un nume valid nu vor fi importate.",
  "import_start_date": "Timp început",
  "included": "Inclus",
  "included services": "Servicii Incluse",
  "initial phase": "Etapa inițială",
  "insert_at_least_3_characters": "Introduceți mai mult de 3 caractere",
  "integrations": "Integrări",
  "invitation_accepted_success": "Invitația a fost acceptată cu succes",
  "invitations": "Invitații",
  "invitation sent": "Invitație transmisă",
  "invitation_sent_message": "Un email nou cu invitație în clinica Dvs a fost transmis.",
  "invite": "Invită",
  "invite existent user": "Invită utilizator existent",
  "invite user": "Invită utilizator",
  "invoice_already_paid": "Acest invoice este deja achitat!",
  "invoice_created": "Un nou invoice a fost creat!",
  "is_clinic_day_off": "Este zi liberă",
  "iscompleted": "Este finisat",
  "is_doctor_holiday": "Doctorul este în vacanță",
  "is urgent": "Este urgent!",
  "isurgent": "Este urgent",
  "is_user_day_off": "Doctorul are zi liberă",
  "it's a day off": "Este zi liberă",
  "jpg or png, max size of 800kb": "JPG or PNG, Mărime maximă 800kb",
  "language": "Limba",
  "languagedesc": "Scrieți mesajul în fiecare limbă disponibilă.",
  "last_changes_list": "Ultimile modificări",
  "last month": "Luna trecută",
  "last name": "Nume",
  "lastname": "Prenume",
  "last week": "Săptămâna trecută",
  "late": "Întârzie",
  "liabilities": "Datorii",
  "link_patient": "Atribuire pacient",
  "list": "Lista",
  "loading statistics": "Se încarcă statistica",
  "log in to your account": "Conectează-te la contul tău",
  "logout": "Ieșire",
  "logout message": "Sunteți sigur(ă) că doriți să ieșiți?",
  "malocclusion": "Malocluzie",
  "manage_payment_method": "Administrează metoda de plată",
  "manager": "Manager",
  "manage_seats": "Administrează locuri",
  "mandible": "Mandibulă",
  "map_all_fields": "Nu ați indicat: {1}",
  "map doctors": "Mapare doctori",
  "map services": "Mapare servicii",
  "maxillary": "Maxilar",
  "menu_crm_help_message": "Acum puteți ridica relațiile cu clienții Dvs la un alt nivel. Dați click aici pentru a deschide panoul CRM unde puteți controla tot fluxul pacienților.",
  "menu_crm_help_title": "Acum și CRM",
  "message": "Textul mesajului",
  "message_exists": "Acest tip de mesaj deja există",
  "message not delivered": "Mesajul nu a fost transmis",
  "messages": "Mesaje SMS",
  "message text": "Textul mesajului",
  "messagetext": "Textul mesajului",
  "message title": "Titlul mesajului",
  "messagetitledesc": "Titlul mesajului este vizibil doar pentru Dvs, pacienții nu vor vedea acest titlu.",
  "message type": "Tipul mesajului",
  "middle phase": "Etapa de mijloc",
  "migrate data from yclients": "Migrare date din Yclients",
  "minutes": "Minute",
  "moizvonki_connect_info": "Moizvonki.ru datele API",
  "moizvonki_username_help": "Adresa de email folosită la logarea în Moizvonki.ru",
  "monday": "Luni",
  "month": "Lună",
  "monthly": "Lunar",
  "months": "Luni",
  "move column to left": "Mută în stânga",
  "move column to right": "Mută în dreapta",
  "name": "Nume",
  "n_contacts_only": "Maximum {1} pacienți",
  "new password": "Parola nouă",
  "new patient": "Adaugă pacient nou",
  "next": "Următorul",
  "next_payment_info": "Plata viitoare în sumă de %{money} va fi încasată la %{time}",
  "no appointment": "Nu are programare",
  "no available time": "Nu este timp liber",
  "no_categories_message": "Nu sunt categorii create :(",
  "no data here yet": "Nu sunt date aici",
  "no debts found": "Nu are datorii",
  "no description": "Nu este descriere",
  "no doctors yet": "Nu este nici un doctor.",
  "no managers yet": "Nu este nici un manager.",
  "no name specified": "Nu este specificat un nume",
  "no_notes": "Nu sunt notițe",
  "no options": "Nu sunt rezultate",
  "no pending invitations": "Nu sunt invitații în așteptare",
  "no phone number": "Nu este indicat",
  "no_purchased_subscription": "Nu sunt abonamente de afișat",
  "no_recent_changes": "Nu sunt modificări recente",
  "no receptionists yet": "Nu este nici un recepționist.",
  "no results": "Nu au fost găsite rezultate",
  "no schedules for this day": "Nu sunt programări pentru această zi",
  "no selected services": "Nu sunt servicii selectate",
  "no_services_message": "Încă nu sunt servicii în această categorie :(",
  "no_sms_alias_message": "Serviciul notificări SMS nu este conectat. Pentru a conecta vă rugăm să ne contactați.",
  "no_sms_messages": "Încă nu sunt mesaje create",
  "note": "Notă",
  "notes": "Notițe",
  "notetext": "Textul notiței",
  "no treatment plan": "Nu are plan de tratament",
  "n_schedules_only": "Maximum {1} programări",
  "n_services_only": "Maximum {1} servicii",
  "number": "Număr",
  "occlusion": "Ocluzie",
  "class": "Clasă",
  "angle class": "Angle Class",
  "of": "din",
  "offers braces services": "Oferă servicii de ortodonție",
  "onetimemessage": "Mesaj expediat o singură dată",
  "onetimemessagedesc": "ATENȚIE! Acest mesaj va fi expediat la toți pacienții o singură dată imediat după ce salvați mesajul",
  "on site": "Pe loc",
  "onsite": "Pe loc",
  "optional": "Opțional",
  "or": "sau",
  "orthodontic plan": "Plan ortodontic",
  "other": "Altele",
  "page_not_found": "Pagina nu a fost găsită",
  "paid": "Achitat",
  "paidamount": "Suma achitată",
  "paid for": "Achitat pentru",
  "partial paid": "Achitat parțial",
  "partialpaid": "Achitat parțial",
  "partner token": "Tokenul de autorizare a partenerului",
  "password": "Parola",
  "passwords_not_equal": "Parola nu coincide",
  "passwordvalidationmessage": "Parola trebuie să conțină litere majuscule, minuscule, cifre și simboluri cu o lungime de minimum 6 caractere",
  "patient": "Pacient",
  "patient first name": "Prenumele pacientului",
  "patient full name": "Nume deplin a pacientului",
  "patient last name": "Numele pacientului",
  "patient name": "Nume pacient",
  "patientname": "Nume pacient",
  "patient_not_found": "Pacientul nu a fost găsit",
  "patient_not_on_site": "Pacinetul nu este în clinică!",
  "patient phone": "Telefon pacient",
  "patientphone": "Telefon pacient",
  "patients": "Pacienți",
  "patients_import_note": "Notă: Pacienții fără număr de telefon nu vor fi importați.",
  "patient_source": "Sursa pacientului",
  "patients per page": "Pacienți per pagină",
  "patients statistics": "Statistica pacienților",
  "patient_tags": "Etichete",
  "pause": "Pauză",
  "pay": "Achită",
  "payinvoice": "A înregistrat o achitare",
  "payment_address1": "Adresa primară",
  "payment_address2": "Adresa secundară",
  "payment_card_holder": "Deținătorul Cardului",
  "payment_card_number": "Numărul Cardului",
  "payment_city": "Oraș",
  "payment_country": "Țara",
  "payment_due": "Scadența plății",
  "payment_frequency": "Cât de des dorești să achiți?",
  "payment_info": "Vei fi taxat astăzi %{sum} pentru %{seats} loc(uri), in total veți avea disponibile %{totalSeats} loc(uri)",
  "payment_info_address": "Adresa de facturare",
  "payment_info_card": "Detaliile Cardului de Plată",
  "payment_info_no_payment": "La finalizarea înregistrării nu se va percepe nici o plată categoric",
  "payment_method": "Metoda de plată",
  "payment_mm": "LL",
  "payment_removal": "Înlăturați %{seats} loc(uri), rămânând cu doar %{leftSeats} loc(uri) disponibile",
  "payments": "Achitări",
  "payment_state": "Județ/Raion",
  "payment_title": "Plăți",
  "payment_valid_till": "Valabil până la",
  "payment_yy": "AA",
  "payment_zip": "Cod Poștal",
  "pending": "Programat",
  "pending delivery": "În așteptare expediere",
  "pending payment": "În așteptare",
  "pendingpayment": "În așteptare",
  "period": "Perioada",
  "personal info": "Detalii pacient",
  "persons": "persoane",
  "phone": "Telefon",
  "phonecall": "Apel telefonic",
  "phone_invalid_message": "Numărul de telefon nu este valid.",
  "phone number": "Număr de telefon",
  "phonenumber": "Număr de telefon",
  "phone records": "Înregistrări telefonice",
  "photo": "Foto",
  "previous": "Înapoi",
  "price": "Preț",
  "priceatexecutiontime": "Prețul inițial",
  "priceatpaymenttime": "Prețul la achitare",
  "print plan": "Printează planul",
  "print receipt": "Printează bon",
  "promotionalmessage": "Mesaj promoțional",
  "promotionalmessagedesc": "Acest mesaj va fi expediat la toți pacienții o singură dată la data selectată mai jos",
  "prosthetics": "Proteze",
  "provided services": "Serviciile oferite",
  "radiograph": "Radiografie",
  "received by": "Incasat de",
  "receiverphone": "Număr de telefon",
  "receivers": "Recipienți",
  "receivers filter": "Filtru recipienți",
  "reception": "Recepționist",
  "receptionist": "Recepționist",
  "receptionists": "Recepție",
  "redirecting to clinic": "Vă redirecționăm la clinică",
  "register payment": "Înregistrează plata",
  "remained": "Rămas",
  "reminder_updated": "Sarcină modificată",
  "removal_date_notice": "Modificările vor intra în vigoare din data de %{date}",
  "remove_notice": "În clinica dvs. sunt înregistrați %{doctors} doctor(i) pentru care trebuie să aveți locuri.",
  "remove_seats": "Înlătură locuri",
  "rename column": "Redenumește coloana",
  "required": "Obligator",
  "required time": "Durata",
  "rescheduled": "Reprogramat",
  "reset": "Resetează",
  "reset password": "Resetează parola",
  "reset password message": "Introduceți adresa de e-mail asociată contului dvs. și vă vom trimite un link pentru a vă reseta parola.",
  "reset_password_message": "Introduceți adresa de e-mail asociată contului dvs. și vă vom trimite un link pentru a vă reseta parola.",
  "responsible": "Responsabil",
  "restore": "Restabilește",
  "restore service": "Restabilire serviciu",
  "retry_payment": "Reîncearcă plata",
  "role for user": "Rolul utilizatorului în clinică",
  "rows per page": "Rânduri pe pagină",
  "saturday": "Sâmbătă",
  "save": "Salvează",
  "saved successfully": "Datele au fost salvate cu succes!",
  "schedule_already_paid": "Programarea a fost deja achitată!",
  "schedule date": "Data programării",
  "schedule hour": "Ora programării",
  "schedule info not found": "Informația despre programare nu a fost găsită",
  "schedule_not_found": "Programarea nu a fost găsită",
  "schedulenotification": "Notificare despre programare",
  "schedulenotificationdesc": "Acest mesaj va fi transmis pacienților cu o zi înainte de programare.",
  "schedules": "Programări",
  "schedules statistics": "Statistica programărilor",
  "schedules stats": "Statutul programărilor",
  "schedule time": "Ora programării",
  "Schedule was deleted": "Programarea a fost ștearsă!",
  "search": "Caută",
  "searching": "Căutăm",
  "search patient": "Caută pacient",
  "seats": "Loc(uri)",
  "seats_available": "Loc(uri) disponibile",
  "security settings": "Setări de securitate",
  "select a clinic": "Alegeți o clinică",
  "select a page": "Selectați o pagină",
  "select category": "Alege o categorie",
  "select color": "Alege o culoare",
  "select doctor": "Alege doctor",
  "select doctor from the list": "Alege doctori din listă",
  "selected_doctor_does_not_provide_this_service": "Doctorul selectat nu presteaza acest serviciu",
  "selected_file_is_not_an_image": "Fisierul selectat nu este o imagine",
  "select patient": "Alege pacient",
  "select phase": "Alege etapa",
  "select teeth for": "Alegeți dinții pentru",
  "select type of data to import": "Selectați ce date doriți să importați",
  "send": "Trimite",
  "send message": "Trimite mesaj",
  "send notification at": "Ora de trimitere a mesajului",
  "sendsmsaction": "A trimis un sms",
  "sendstatus": "Statut",
  "send time": "Timpul trimiterii",
  "sent by": "Trimis de",
  "sentby": "Trimis de",
  "service": "Serviciu",
  "service_already_exists_on_schedule": "Acest serviciu deja există pentru programarea dată.",
  "service information": "Detalii serviciu",
  "service name": "Denumire serviciu",
  "servicename": "Denumire serviciu",
  "service_not_provided_by_user": "Serviciul nu este oferit de doctor",
  "service price": "Prețul",
  "services": "Servicii",
  "services statistics": "Statistica serviciilor",
  "service type": "Tip serviciu",
  "set_as_default": "Setează card implicit",
  "settings": "Setări",
  "setting_tags_current": "Etichete curente",
  "setting_tags_field": "Adaugă etichetă",
  "setting_tags_helper": "Introduceți denumire etichetă și apăsați Enter pentru a adăuga",
  "setting_tags_share_all": "Partajați toate etichetele",
  "share_tags_success": "Etichetele au fost partajate cu clinica {1}",
  "show_doctor_on_confirmation": "Afișează numele doctorului pe pagina de confirmare a programării",
  "show in calendar": "Arată în calendar",
  "sign up": "Crează cont",
  "something_went_wrong": "Ooops, ceva nu a mers bine!",
  "source": "Sursa",
  "spoken_language": "Limba vorbită",
  "spokenlanguage": "Limba vorbită",
  "start_migration_message": "La click pe butonul START noi vom importa toate datele din Yclients în EasyPlan. Acest proces poate dura ceva timp, Dvs. puteți continua să explorați aplicația iar noi vă vom notifica când totul va fi gata.",
  "start time": "Început",
  "status": "Statut",
  "statuses": "Statuturi",
  "step 1": "Pasul 1.",
  "step 2": "Pasul 2.",
  "step 3": "Pasul 3.",
  "step 4": "Pasul 4.",
  "sunday": "Duminică",
  "surgery": "Intervenție chirurgicală",
  "switchclinic": "A schimbat clinica",
  "switch_month_plan": "Treci la plan lunar",
  "switch_year_plan": "Treci la plan anual și economisește",
  "tax_prorated_info": "Loc nou la preț de %{price}/lună fiecare, calculat proporțional pentru %{days} zile",
  "tech_support": "Suport tehnic",
  "this_cabinet_has_no_doctors": "Nu sunt doctori în acest cabinet",
  "this month": "Luna curentă",
  "this week": "Săptămâna curentă",
  "thursday": "Joi",
  "time": "Timp",
  "time before schedule": "Timp înainte de programare",
  "time zone": "Fus orar",
  "title": "Titlu",
  "to": "pînă la",
  "today": "Astăzi",
  "tooth": "Dintele %{tooth}",
  "toothid": "Dintele",
  "totalamount": "Suma totală",
  "total income": "Venit total",
  "transaction_unsuccessful": "Tranzacție nereușită",
  "treatment": "Tratament",
  "treatment plan": "Plan de tratament",
  "treatment type": "Tip de tratament",
  "tuesday": "Marți",
  "type_here": "Scrie aici",
  "type to search": "Scrie pentru a căuta",
  "type_to_search": "Scrie pentru a căuta...",
  "undo_payment": "Anulează plata",
  "undo_payment_confirm_message": "Toate plățile pentru aceeași factură vor fi anulate. Sunteți sigur(ă) că doriți să anulați plata?",
  "unknown": "Necunoscut",
  "unknown delivery status": "Statut necunoscut",
  "unmapped items will not be imported": "Elementele ne partajate nu vor fi importate",
  "update": "Actualizați",
  "updatebracesplanaction": "A fost modificat planul ortodontic",
  "updatedorthodonticplan": "A fost editat planul de tratament",
  "updateinvoiceaction": "A fost modificat o factură",
  "updateinvoiceserviceaction": "A fost modificat un serviciu la factură",
  "updatenoteaction": "A editat o notiță",
  "updatepatientaction": "A modificat pacientul",
  "updateplanserviceaction": "A modificat un serviciu din planul de tratament",
  "updatescheduleaction": "A modificat o programare",
  "upload csv file": "Încărcați fișierul CSV",
  "upload file": "Selectează fișier (.xls, .xlsx)",
  "upload image": "Alege imagine",
  "user": "Utilizator",
  "username": "Nume utilizator",
  "user_not_found": "Utilizatorul nu a fost găsit",
  "users": "Utilizatori",
  "value": "Valoarea",
  "value in easyplan": "Valoarea în EasyPlan",
  "value in your file": "Valoarea în fișier",
  "value_less_then": "Valoarea trebuie să fie mai mică de",
  "value_more_then": "Valoarea trebuie să fie mai mare de",
  "version": "Versiunea",
  "view": "Detalii",
  "viewactivitylogs": "A vizualizat jurnalul activităților",
  "viewappointment": "A vizualizat o programare",
  "viewappointments": "A vizualizat programările",
  "viewcategory": "A vizualizat o categorie",
  "view debt": "Vezi datoria",
  "view details": "Detalii",
  "viewdoctorsstatistics": "A vizualizat statistica doctorilor",
  "viewgeneralstatistics": "A vizualizat statistica generală",
  "view_more": "Vezi tot",
  "viewpatient": "A vizualizat un pacient",
  "viewpatients": "A vizualizat toți pacienții",
  "viewservice": "A vizualizat un serviciu",
  "viewservices": "A vizualizat toate serviciile",
  "viewservicesstatistics": "A vizualizat statistica serviciilor",
  "viewuser": "A vizualizat un utilizator",
  "viewusers": "A vizualizat toți utilizatorii",
  "visible_states": "Statuturile vizibile",
  "visitdate": "Data vizitei",
  "visits": "Vizite",
  "waiting": "În așteptare",
  "waiting for patient": "În așteptare pacient",
  "waitingforpatient": "În așteptare pacient",
  "we are ready to start": "Suntem gata de migrarea datelor",
  "wednesday": "Miercuri",
  "week": "Săptămână",
  "week schedules": "Programările pentru o săptămână",
  "welcome to easyplan": "Bun venit în EasyPlan",
  "why schedule is canceled": "De ce a fost anulată programarea",
  "work hours": "Orarul de lucru",
  "working hours": "Program de lucru",
  "wrong_username_or_password": "Wrong email or password",
  "yclients_auth_explanation": "Pentru a putea importa datele din Yclients în EasyPlan avem nevoie de acces la contul Dvs de Yclients.",
  "year": "An",
  "yearly": "Anual",
  "yes": "Da",
  "yesterday": "Ieri",
  "employer_certificate": "Certificat angajator",
  "address": "Adresa",
  "identity_card": "Carte de identitate",
  "series": "Serie",
  "idnp": "IDNP",
  "trial_days_left_notification": "Zile de probă rămase",
  "trial_day_left_notification": "Zi de probă rămasă",
  "subscription_canceled": "Subscripție anulată",
  "total": "Total",
  "user-comment": "Comentariu utilizator",
  "total-prepayment": "Total avans",
  "total-debt": "Total datorii",
  "total-cost": "Pret total",
  "cash": "Numerar",
  "card": "Card bancar",
  "transfer": "Transfer",
  "gift_certificate": "Certificat Cadou",
  "select_payment_method": "Selectati metoda de plata",
  "reports": "Rapoarte",
  "user_comment": "Comentariu utilizator",
  "export_excel": "Exportă ca .xlsx",
  "consultation_appointment": "Programare la conslutare",
  "consultation_service": "Serviciu de consultare",
  "pending_consultations": "Consultații în așteptare",
  "patient_guide": "Ghidul pacientului",
  "consultations": "Consultații"
}
